[
  {
    "img": "https://cn.bing.com/th?id=OHR.ManhattanView_ZH-CN3156325644_UHD.jpg&rf=LaDigue_UHD.jpg&pid=hp&w=3840&h=2160&rs=1&c=4",
    "date": "20220124",
    "copyright": "灯光璀璨的曼哈顿下城，美国纽约 (© New York On Air/Offset/Shutterstock)"
  },
  {
    "img": "https://cn.bing.com/th?id=OHR.MeotoIwa_ZH-CN3126370410_UHD.jpg&rf=LaDigue_UHD.jpg&pid=hp&w=3840&h=2160&rs=1&c=4",
    "date": "20220123",
    "copyright": "海岸旁的二见浦夫妇岩，日本三重县 (© Marco Gaiotti/plainpicture)"
  },
  {
    "img": "https://cn.bing.com/th?id=OHR.LesserAntilles_ZH-CN3012679657_UHD.jpg&rf=LaDigue_UHD.jpg&pid=hp&w=3840&h=2160&rs=1&c=4",
    "date": "20220122",
    "copyright": "蔚蓝海域中的马提尼克岛，加勒比海 (© Airpano LLC/Amazing Aerial Agency)"
  },
  {
    "img": "https://cn.bing.com/th?id=OHR.HuggingDay_ZH-CN2984681593_UHD.jpg&rf=LaDigue_UHD.jpg&pid=hp&w=3840&h=2160&rs=1&c=4",
    "date": "20220121",
    "copyright": "草丛中的母狮和它的幼崽，南非 (© Andrew Coleman/Getty Images)"
  },
  {
    "img": "https://cn.bing.com/th?id=OHR.GrahamAdelie_ZH-CN2945763969_UHD.jpg&rf=LaDigue_UHD.jpg&pid=hp&w=3840&h=2160&rs=1&c=4",
    "date": "20220120",
    "copyright": "格雷厄姆海峡的阿德利企鹅，南极洲南极半岛 (© Nick Garbutt/Minden Pictures)"
  },
  {
    "img": "https://cn.bing.com/th?id=OHR.SaintElias_ZH-CN2861097596_UHD.jpg&rf=LaDigue_UHD.jpg&pid=hp&w=3840&h=2160&rs=1&c=4",
    "date": "20220119",
    "copyright": "克卢恩国家公园保护区的山脉和冰川，加拿大育空地区 (© Design Pics Inc/Alamy)"
  },
  {
    "img": "https://cn.bing.com/th?id=OHR.BurghausenWinter_ZH-CN2822501718_UHD.jpg&rf=LaDigue_UHD.jpg&pid=hp&w=3840&h=2160&rs=1&c=4",
    "date": "20220118",
    "copyright": "博格豪森镇和萨尔察赫河，德国巴伐利亚州 (© Harald Nachtmann/Moment/Getty Images)"
  },
  {
    "img": "https://cn.bing.com/th?id=OHR.RydalWater_ZH-CN2787617470_UHD.jpg&rf=LaDigue_UHD.jpg&pid=hp&w=3840&h=2160&rs=1&c=4",
    "date": "20220117",
    "copyright": "莱达尔湖, 英格兰坎布里亚郡湖区 (© Tranquillian1/iStock/Getty Images Plus)"
  },
  {
    "img": "https://cn.bing.com/th?id=OHR.BoguraChili_ZH-CN2707755390_UHD.jpg&rf=LaDigue_UHD.jpg&pid=hp&w=3840&h=2160&rs=1&c=4",
    "date": "20220116",
    "copyright": "农场上晾晒的红辣椒，孟加拉国博格拉县 (© Amazing Aerial Agency/Offset/Shutterstock)"
  },
  {
    "img": "https://cn.bing.com/th?id=OHR.BigHole_ZH-CN2671071218_UHD.jpg&rf=LaDigue_UHD.jpg&pid=hp&w=3840&h=2160&rs=1&c=4",
    "date": "20220115",
    "copyright": "苏阿海沟，萨摩亚乌波卢岛南海岸 (© Chris McLennan/Alamy)"
  },
  {
    "img": "https://cn.bing.com/th?id=OHR.SaCalobra_ZH-CN0945855556_UHD.jpg&rf=LaDigue_UHD.jpg&pid=hp&w=3840&h=2160&rs=1&c=4",
    "date": "20220114",
    "copyright": "通往萨卡洛布拉湾的路，西班牙马约卡岛 (© Tolo Balaguer/agefotostock)"
  },
  {
    "img": "https://cn.bing.com/th?id=OHR.TasiilaqAurora_ZH-CN0330057121_UHD.jpg&rf=LaDigue_UHD.jpg&pid=hp&w=3840&h=2160&rs=1&c=4",
    "date": "20220113",
    "copyright": "搁浅船只上空的极光，格陵兰岛塔西拉克 (© Shane P. White/Minden Pictures)"
  },
  {
    "img": "https://cn.bing.com/th?id=OHR.FanjingStairs_ZH-CN0360402048_UHD.jpg&rf=LaDigue_UHD.jpg&pid=hp&w=3840&h=2160&rs=1&c=4",
    "date": "20220112",
    "copyright": "梵净山，中国西南部 (© zhuxiaophotography/Shutterstock)"
  },
  {
    "img": "https://cn.bing.com/th?id=OHR.PorcupineWillow_ZH-CN0280041973_UHD.jpg&rf=LaDigue_UHD.jpg&pid=hp&w=3840&h=2160&rs=1&c=4",
    "date": "20220111",
    "copyright": "爬上柳树枝头的豪猪，美国阿拉斯加 (© Design Pics/Danita Delimont)"
  },
  {
    "img": "https://cn.bing.com/th?id=OHR.SkiTouring_ZH-CN0237169285_UHD.jpg&rf=LaDigue_UHD.jpg&pid=hp&w=3840&h=2160&rs=1&c=4",
    "date": "20220110",
    "copyright": "在高地陶恩山脉的滑雪旅行，奥地利巴德加斯坦 (© RooM the Agency/Alamy)"
  },
  {
    "img": "https://cn.bing.com/th?id=OHR.RiceBangladesh_ZH-CN0196473460_UHD.jpg&rf=LaDigue_UHD.jpg&pid=hp&w=3840&h=2160&rs=1&c=4",
    "date": "20220109",
    "copyright": "正在晾晒的大米，孟加拉国达卡 (© Amazing Aerial Agency/Offset by Shutterstock)"
  },
  {
    "img": "https://cn.bing.com/th?id=OHR.WinterBison_ZH-CN0120689382_UHD.jpg&rf=LaDigue_UHD.jpg&pid=hp&w=3840&h=2160&rs=1&c=4",
    "date": "20220108",
    "copyright": "黄石国家公园的美洲野牛，美国怀俄明州 (© Steve Gettle/Minden Pictures)"
  },
  {
    "img": "https://cn.bing.com/th?id=OHR.FortedeSao_ZH-CN0093358703_UHD.jpg&rf=LaDigue_UHD.jpg&pid=hp&w=3840&h=2160&rs=1&c=4",
    "date": "20220107",
    "copyright": "纳扎雷灯塔，葡萄牙 (© Richard A Lock/Getty Images)"
  },
  {
    "img": "https://cn.bing.com/th?id=OHR.LakeKochelsee_ZH-CN0004970986_UHD.jpg&rf=LaDigue_UHD.jpg&pid=hp&w=3840&h=2160&rs=1&c=4",
    "date": "20220106",
    "copyright": "冬日里的科赫尔湖，德国巴伐利亚州 (© Reinhard Schmid/eStock Photo)"
  },
  {
    "img": "https://cn.bing.com/th?id=OHR.MountainToucan_ZH-CN9939482570_UHD.jpg&rf=LaDigue_UHD.jpg&pid=hp&w=3840&h=2160&rs=1&c=4",
    "date": "20220105",
    "copyright": "树干上的扁嘴山巨嘴鸟，厄瓜多尔 (© Tui De Roy/Minden Pictures)"
  },
  {
    "img": "https://cn.bing.com/th?id=OHR.BorregoBadlands_ZH-CN9913349081_UHD.jpg&rf=LaDigue_UHD.jpg&pid=hp&w=3840&h=2160&rs=1&c=4",
    "date": "20220104",
    "copyright": "安沙波利哥沙漠州立公园，美国加利福尼亚州 (© Tom Hogan/plainpicture)"
  },
  {
    "img": "https://cn.bing.com/th?id=OHR.LickObservatory_ZH-CN9676762110_UHD.jpg&rf=LaDigue_UHD.jpg&pid=hp&w=3840&h=2160&rs=1&c=4",
    "date": "20220103",
    "copyright": "汉密尔顿山顶的利克天文台，美国加利福尼亚州 (© Jeffrey Lewis/Tandem Stills + Motion)"
  },
  {
    "img": "https://cn.bing.com/th?id=OHR.SnowyPrague_ZH-CN9794475183_UHD.jpg&rf=LaDigue_UHD.jpg&pid=hp&w=3840&h=2160&rs=1&c=4",
    "date": "20220102",
    "copyright": "雪后的布拉格，捷克共和国 (© benkrut/Getty Images)"
  },
  {
    "img": "https://cn.bing.com/th?id=OHR.JonesBeachHarpSeal_ZH-CN9584238333_UHD.jpg&rf=LaDigue_UHD.jpg&pid=hp&w=3840&h=2160&rs=1&c=4",
    "date": "20220101",
    "copyright": "睡在海滩上的竖琴海豹，纽约长岛 (© Vicki Jauron, Babylon and Beyond Photography/Getty Images)"
  }
]